data_toolset/__init__.py
data_toolset/main.py
data_toolset/utils/__init__.py
data_toolset/utils/avro.py
data_toolset/utils/base.py
data_toolset/utils/mixins.py
data_toolset/utils/parquet.py
data_toolset/utils/utils.py
data_toolset-0.1.7.dist-info/LICENSE
data_toolset-0.1.7.dist-info/METADATA
data_toolset-0.1.7.dist-info/WHEEL
data_toolset-0.1.7.dist-info/entry_points.txt
data_toolset-0.1.7.dist-info/RECORD
