Metadata-Version: 2.1
Name: data-toolset
Version: 0.1.7
Summary: 
Home-page: https://github.com/luminousmen/data-toolset
License: MIT
Author: Kirill Bobrov
Author-email: miaplanedo@gmail.com
Requires-Python: >=3.8.1,<4.0.0
Classifier: License :: OSI Approved :: MIT License
Classifier: Programming Language :: Python :: 3
Classifier: Programming Language :: Python :: 3.9
Classifier: Programming Language :: Python :: 3.10
Classifier: Programming Language :: Python :: 3.11
Requires-Dist: arrow (>=1.2.3,<2.0.0)
Requires-Dist: cython (>=3.0.2,<4.0.0)
Requires-Dist: duckdb (>=0.8.1,<0.10.0)
Requires-Dist: fastavro (>=1.7.3,<2.0.0)
Requires-Dist: polars (>=0.19.7,<0.20.0)
Requires-Dist: pyarrow (>=13.0.0,<14.0.0)
Requires-Dist: python-snappy (>=0.6.1,<0.7.0)
Requires-Dist: tox (>=4.11.1,<5.0.0)
Project-URL: Repository, https://github.com/luminousmen/data-toolset
